Flask_Cache_Buster-1.0.1.dist-info/DESCRIPTION.rst
Flask_Cache_Buster-1.0.1.dist-info/METADATA
Flask_Cache_Buster-1.0.1.dist-info/RECORD
Flask_Cache_Buster-1.0.1.dist-info/WHEEL
Flask_Cache_Buster-1.0.1.dist-info/metadata.json
Flask_Cache_Buster-1.0.1.dist-info/top_level.txt
flask_cache_buster/__init__.py
