Metadata-Version: 2.0
Name: Flask-Cache-Buster
Version: 1.0.1
Summary: Flask extension calculates new cache busted path for static files
Home-page: https://github.com/daxlab/Flask-Cache-Buster
Author: UNKNOWN
Author-email: UNKNOWN
License: MIT
Platform: UNKNOWN
Requires-Dist: Flask
